{
    "status": 200,
    "data": {
        "_id": {
            "$oid": "536b8979682cfa5294504719"
        },
        "app_id": "53280f81c8f25a47fe2e234e",
        "title": "Dashboard",
        "rows": [
            {
                "height": "200px",
                "widgets": [
                    {
                        "_id": {
                            "$oid": "536b86d0682cfa5294504712"
                        },
                        "widgetType": "bar",
                        "title": "Platforms",
                        "rows": [],
                        "cols": [
                            {
                                "dimension": {
                                    "field": "platform"
                                },
                                "aggregation": {
                                    "type": "category"
                                }
                            }
                        ],
                        "measures": [
                            "users_count"
                        ],
                        "filterBy": "p",
                        "width": 4
                    },
                    {
                        "_id": {
                            "$oid": "536b87af682cfa5294504713"
                        },
                        "widgetType": "row",
                        "title": "Countries",
                        "rows": [
                            {
                                "dimension": {
                                    "field": "country"
                                },
                                "aggregation": {
                                    "type": "category"
                                }
                            }
                        ],
                        "cols": [],
                        "measures": [
                            "users_count"
                        ],
                        "filterBy": "c",
                        "width": 4
                    },
                    {
                        "_id": {
                            "$oid": "536b8809682cfa5294504714"
                        },
                        "widgetType": "pie",
                        "title": "Gender",
                        "rows": [
                            {
                                "dimension": {
                                    "field": "gender"
                                },
                                "aggregation": {
                                    "type": "category"
                                }
                            }
                        ],
                        "cols": [],
                        "measures": [
                            "users_count"
                        ],
                        "filterBy": "g",
                        "width": 4
                    }
                ]
            },
            {
                "height": "300px",
                "widgets": [
                    {
                        "_id": {
                            "$oid": "536b884f682cfa5294504715"
                        },
                        "widgetType": "area",
                        "title": "Revenue",
                        "rows": [
                            {
                                "dimension": {
                                    "field": "platform"
                                },
                                "aggregation": {
                                    "type": "category"
                                }
                            }
                        ],
                        "cols": [
                            {
                                "dimension": {
                                    "field": "date"
                                },
                                "aggregation": {
                                    "type": "date",
                                    "date_type": "Day"
                                }
                            }
                        ],
                        "measures": [
                            "total_revenue"
                        ],
                        "filterBy": "p",
                        "width": 6
                    },
                    {
                        "_id": {
                            "$oid": "536b8880682cfa5294504716"
                        },
                        "widgetType": "row",
                        "title": "Sources",
                        "rows": [
                            {
                                "dimension": {
                                    "field": "gender"
                                },
                                "aggregation": {
                                    "type": "category"
                                }
                            },
                            {
                                "dimension": {
                                    "field": "source"
                                },
                                "aggregation": {
                                    "type": "category"
                                }
                            }
                        ],
                        "cols": [],
                        "measures": [
                            "users_count"
                        ],
                        "filterBy": "s",
                        "width": 6
                    }
                ]
            },
            {
                "height": "300px",
                "widgets": [
                    {
                        "_id": {
                            "$oid": "536b88b5682cfa5294504717"
                        },
                        "widgetType": "line",
                        "title": "Registrations",
                        "rows": [
                            {
                                "dimension": {
                                    "field": "app_version"
                                },
                                "aggregation": {
                                    "type": "category"
                                }
                            }
                        ],
                        "cols": [
                            {
                                "dimension": {
                                    "field": "date"
                                },
                                "aggregation": {
                                    "type": "date",
                                    "date_type": "Day"
                                }
                            }
                        ],
                        "measures": [
                            "users_count"
                        ],
                        "filterBy": "r",
                        "width": 7
                    },
                    {
                        "_id": {
                            "$oid": "536b88e8682cfa5294504718"
                        },
                        "widgetType": "pivot",
                        "title": "KPIs",
                        "rows": [
                            {
                                "dimension": {
                                    "field": "date"
                                },
                                "aggregation": {
                                    "type": "date",
                                    "date_type": "Day"
                                }
                            }
                        ],
                        "cols": [
                            {
                                "dimension": {
                                    "field": "platform"
                                },
                                "aggregation": {
                                    "type": "category"
                                }
                            }
                        ],
                        "measures": [
                            "total_revenue",
                            "users_count"
                        ],
                        "filterBy": "r",
                        "width": 5
                    }
                ]
            }
        ]
    }
}